README.rst
setup.py
sshdeploy/__init__.py
sshdeploy/authkeys.py
sshdeploy/key.py
sshdeploy/main.py
sshdeploy/manual.rst
sshdeploy/prefs.py
sshdeploy/utils.py
sshdeploy.egg-info/PKG-INFO
sshdeploy.egg-info/SOURCES.txt
sshdeploy.egg-info/dependency_links.txt
sshdeploy.egg-info/entry_points.txt
sshdeploy.egg-info/not-zip-safe
sshdeploy.egg-info/requires.txt
sshdeploy.egg-info/top_level.txt