Metadata-Version: 1.1
Name: sshdeploy
Version: 1.1.4
Summary: Generates and distributes SSH keys.
Home-page: http://nurdletech.com/linux-utilities/sshdeploy
Author: Ken Kundert
Author-email: sshdeploy@nurdletech.com
License: GPLv3+
Download-URL: https://github.com/kenkundert/sshdeploy/tarball/master
Keywords: ssh,keys
Platform: UNKNOWN
Classifier: Development Status :: 3 - Alpha
Classifier: Environment :: Console
Classifier: Intended Audience :: End Users/Desktop
Classifier: License :: OSI Approved :: GNU General Public License v3 or later (GPLv3+)
Classifier: Natural Language :: English
Classifier: Operating System :: POSIX :: Linux
Classifier: Programming Language :: Python :: 3.5
Classifier: Topic :: Utilities
